<?xml version="1.0" encoding="windows-1252" standalone="yes"?><!-- Generated by abcexcel-->  
<Records>
  <Record>
    <Row
      A="id"
      B="status"
      C="test?"
      D="complete"
      E="panels_completed"
      F="ckm_campaign_id"
      G="ckm_key"
      H="ckm_subid"
      I="leadid_token"
      J="first_name"
      K="last_name"
      L="name"
      M="title"
      N="age"
      O="email_address"
      P="phone"
      Q="phone_type"
      R="phone2"
      S="phone2_type"
      T="best_time_to_call"
      U="opt_in"
      V="address"
      W="city"
      X="state"
      Y="country"
      Z="zip_code"
      AA="ip_address"
      AB="highest_level_of_education"
      AC="currently_in_school"
      AD="primary_language"
      AE="undergraduate_gpa"
      AF="year_graduated_from_high_school"
      AG="years_of_work_experience"
      AH="currently_employed"
      AI="income_range"
      AJ="have_teaching_certificate"
      AK="nurse"
      AL="nursing_have_BS"
      AM="nursing_have_RN"
      AN="nursing_state_RN_license"
      AO="nursing_have_1000_hours"
      AP="nursing_comfortable_blood"
      AQ="nursing_comfortable_needles"
      AR="nursing_comfortable_patient"
      AS="classroom_experience_want"
      AT="how_soon_planning_to_enroll"
      AU="area_of_study"
      AV="area_of_concentration"
      AW="degree_sought"
      AX="certification_sought"
      AY="program_sought"
      AZ="program_sought_1"
      BA="program_sought_2"
      BB="program_sought_3"
      BC="program_sought_4"
      BD="program_sought_5"
      BE="program_sought_6"
      BF="program_sought_7"
      BG="program_sought_8"
      BH="program_sought_9"
      BI="program_sought_10"
      BJ="program_sought_11"
      BK="program_sought_12"
      BL="program_sought_SHD_code"
      BM="program_sought_CCI_code"
      BN="program_sought_Kaplan_code"
      BO="program_sought_NCU_code"
      BP="program_sought_Phoenix_code"
      BQ="us_citizen"
      BR="affiliated_with_us_military"
      BS="type_of_military_affiliation"
      BT="schools_interested_in"
      BU="lead_id"
      BV="price"
      BW="redirect"
      BX="kaplan_sif_id"
      BY="kaplan_sif_version_id"
      BZ="created_at"
      CA="updated_at"
    />
  </Record>
  <Record>
    <Row
      A="1"
      B="active"
      C="t"
      J="Brianbefn"
      K="Dunn"
      O="brentdunn5s4@comcast.net"
      P="2096275934"
      T="9:00 AM"
      U="t"
      V="73 james ct"
      W="Belmont"
      X="California"
      Y="United States"
      Z="94002"
      AB="5"
      AT="01months"
      AU="CJ"
      AW="M"
      AY="MSCJ_GICJ"
      BB="MSCJ_GICJ"
      BQ="t"
      BR="f"
      BS="No"
      BX="279"
      BY="2135"
      BZ="2012-10-31 23:08:55.037521"
      CA="2012-10-31 23:11:30.9131"
    />
  </Record>
  <Record>
    <Row
      A="4"
      B="education"
      C="t"
      I="79BB41C9-DB58-2F61-6EEA-B2E4B5AF78EE"
      J="Brianbens"
      K="Dunns"
      O="brent2@gmail.com"
      P="2098328654"
      Q="CELL"
      U="t"
      V="73 james ct"
      W="Belmont"
      X="AL"
      Y="USA"
      Z="94002"
      AB="2"
      AC="f"
      AD="English"
      AF="1983"
      AT="1"
      AU="5"
      AW="B"
      AY="AMAOL"
      BO="AMAOL"
      BQ="t"
      BR="f"
      BZ="2012-11-01 00:11:48.199723"
      CA="2012-11-01 00:13:07.200822"
    />
  </Record>
  <Record>
    <Row
      A="5"
      B="active"
      C="t"
      J="benben"
      K="Dunn"
      O="brentdunn232@comcast.net"
      P="2098328654"
      R="2098328654"
      T="evening"
      U="t"
      V="73 james ct"
      W="Belmont"
      X="CA"
      Y="USA"
      Z="94002"
      AB="3"
      AT="1 Month"
      AU="4"
      AW="5"
      BC="HSLPPHDB"
      BZ="2012-11-01 00:13:14.117134"
      CA="2012-11-01 00:13:59.659562"
    />
  </Record>
  <Record>
    <Row
      A="6"
      B="active"
      C="t"
      I="79BB41C9-DB58-2F61-6EEA-B2E4B5AF78EE"
      J="benbenb"
      K="Dunn"
      O="brentdun2341@comcast.net"
      P="2098328654"
      Q="BUSN"
      V="73 james ct"
      W="Belmont"
      X="California"
      Y="United States"
      Z="94002"
      AB="2"
      AC="f"
      AD="English"
      AF="1984"
      AT="1"
      AU="5"
      AW="M"
      AY="ACAOL"
      BQ="t"
      BR="f"
      BZ="2012-11-01 00:14:46.493551"
      CA="2012-11-01 00:15:12.614253"
    />
  </Record>
  <Record>
    <Row
      A="7"
      B="active"
      C="t"
      J="benen"
      K="Dunn"
      O="brentdu234234nn@comcast.net"
      P="2098328654"
      T="10:00 AM"
      U="t"
      V="73 james ct"
      W="Belmont"
      X="California"
      Y="United States"
      Z="94002"
      AB="6"
      AT="01months"
      AU="PEP"
      AW="M"
      AY="BSEPM"
      BI="BSEPM"
      BQ="t"
      BR="f"
      BS="No"
      BX="279"
      BY="2133"
      BZ="2012-11-01 00:36:47.288024"
      CA="2012-11-01 00:37:17.047541"
    />
  </Record>
  <Record>
    <Row
      A="10"
      B="active"
      C="t"
      J="ckmtest"
      K="Dunn"
      O="brentdunn@comcast.net"
      P="2098328654"
      T="9:00 AM"
      U="t"
      V="73 james ct"
      W="Belmont"
      X="California"
      Y="United States"
      Z="94002"
      AB="6"
      AT="01months"
      AU="BIZ"
      AW="M"
      AY="MBA_ENT"
      BA="MBA_ENT"
      BQ="t"
      BR="f"
      BS="No"
      BX="279"
      BY="2135"
      BZ="2012-11-01 20:52:53.230334"
      CA="2012-11-01 20:53:24.783486"
    />
  </Record>
  <Record>
    <Row
      A="93"
      B="education"
      C="t"
      J="ckmtest"
      K="Dunn"
      O="brentdunn@comcast.net"
      P="2098328654"
      T="10:00 AM"
      U="t"
      V="73 james ct"
      W="Belmont"
      X="California"
      Y="United States"
      Z="94002"
      AB="3"
      AT="01months"
      AU="PEP"
      AW="B"
      AY="MSEP"
      BI="MSEP"
      BQ="t"
      BR="f"
      BS="No"
      BX="279"
      BY="2135"
      BZ="2012-11-03 21:45:52.53833"
      CA="2012-11-03 22:38:38.26178"
    />
  </Record>
  <Record>
    <Row
      A="100"
      B="active"
      C="t"
      J="ckmtest"
      K="Dunn"
      O="brentdunn@comcast.net"
      P="2098328654"
      T="9:00 AM"
      U="t"
      V="73 James Ct."
      W="Tracy"
      X="California"
      Y="United States"
      Z="95376-1336"
      AB="3"
      AT="01months"
      AU="PEP"
      AW="M"
      AY="BSEPM"
      BI="BSEPM"
      BQ="t"
      BR="f"
      BS="No"
      BX="279"
      BY="2133"
      BZ="2012-11-03 23:08:25.406392"
      CA="2012-11-03 23:09:49.638528"
    />
  </Record>
  <Record>
    <Row
      A="101"
      B="active"
      C="t"
      J="ckmtest"
      K="Dunn"
      O="brentdunn@comcast.net"
      P="2098328654"
      R="2098328654"
      T="afternoon"
      U="t"
      V="73 James Ct."
      W="Tracy"
      X="CA"
      Y="USA"
      Z="95376-1336"
      AB="1"
      AT="1"
      AU="4"
      AW="5"
      AY="CISPHDB"
      BC="CISPHDB"
      BZ="2012-11-03 23:10:45.730992"
      CA="2012-11-03 23:11:41.8985"
    />
  </Record>
  <Record>
    <Row
      A="102"
      B="active"
      C="t"
      I="1F07E859-D2F7-4E35-33E0-627701A9C058"
      J="ckmtest"
      K="Dunn"
      O="brentdunn@comcast.net"
      P="2098328654"
      Q="CELL"
      U="t"
      V="73 James Ct."
      W="Tracy"
      X="CA"
      Y="USA"
      Z="95376-1336"
      AB="2"
      AC="f"
      AD="English"
      AF="1983"
      AT="1"
      AU="5"
      AW="M"
      AY="ACBOL"
      AZ="ACBOL"
      BQ="t"
      BR="f"
      BZ="2012-11-03 23:12:09.192361"
      CA="2012-11-03 23:13:09.825342"
    />
  </Record>
  <Record>
    <Row
      A="110"
      B="active"
      C="t"
      J="ckmtest"
      K="Dunn"
      O="brentdunn@comcast.net"
      P="2098328654"
      T="9:00 AM"
      U="t"
      V="73 james ct"
      W="Belmont"
      X="California"
      Y="United States"
      Z="94002"
      AB="3"
      AT="01months"
      AU="CJ"
      AW="B"
      AY="MSCJ_CORR"
      BB="MSCJ_CORR"
      BQ="t"
      BR="f"
      BS="No"
      BX="279"
      BY="2135"
      BZ="2012-11-04 00:07:45.757586"
      CA="2012-11-04 00:08:14.352126"
    />
  </Record>
  <Record>
    <Row
      A="2"
      AU="1"
      AW="B"
      BZ="2012-11-01 00:11:37.815205"
      CA="2012-11-01 00:11:37.815205"
    />
  </Record>
  <Record>
    <Row
      A="3"
      AU="4"
      AW="B"
      BZ="2012-11-01 00:11:42.947133"
      CA="2012-11-01 00:11:42.947133"
    />
  </Record>
  <Record>
    <Row
      A="8"
      AU="4"
      AW="B"
      BZ="2012-11-01 17:26:54.739179"
      CA="2012-11-01 17:26:54.739179"
    />
  </Record>
  <Record>
    <Row
      A="9"
      B="study"
      AT="1"
      AU="4"
      AW="4"
      BB="CISDBA"
      BC="AAPHDB"
      BZ="2012-11-01 20:35:55.097202"
      CA="2012-11-01 20:36:03.967236"
    />
  </Record>
  <Record>
    <Row
      A="11"
      B="federal"
      AB="5"
      AU="2"
      AW="A"
      BQ="t"
      BR="f"
      BZ="2012-11-01 21:51:53.612408"
      CA="2012-11-01 21:52:14.458408"
    />
  </Record>
  <Record>
    <Row
      A="12"
      B="education"
      AB="4"
      AU="2"
      AW="B"
      BZ="2012-11-01 22:52:30.432937"
      CA="2012-11-01 22:52:38.928814"
    />
  </Record>
  <Record>
    <Row
      A="13"
      B="federal"
      AB="6"
      AU="3"
      AW="M"
      BQ="f"
      BR="f"
      BZ="2012-11-01 23:10:46.340246"
      CA="2012-11-01 23:11:09.048316"
    />
  </Record>
  <Record>
    <Row
      A="14"
      AU="5"
      AW="M"
      BZ="2012-11-01 23:38:48.984896"
      CA="2012-11-01 23:38:48.984896"
    />
  </Record>
  <Record>
    <Row
      A="15"
      AU="2"
      AW="M"
      BZ="2012-11-01 23:38:57.530256"
      CA="2012-11-01 23:38:57.530256"
    />
  </Record>
  <Record>
    <Row
      A="16"
      AU="5"
      AW="A"
      BZ="2012-11-01 23:40:46.0604"
      CA="2012-11-01 23:40:46.0604"
    />
  </Record>
  <Record>
    <Row
      A="17"
      B="education"
      AB="4"
      AT="1"
      AU="4"
      AW="2"
      BA="GPSYMPSY"
      BC="AAPHDB"
      BZ="2012-11-01 23:53:16.718617"
      CA="2012-11-01 23:54:13.809505"
    />
  </Record>
  <Record>
    <Row
      A="18"
      AU="1"
      AW="A"
      BZ="2012-11-01 23:54:54.879444"
      CA="2012-11-01 23:54:54.879444"
    />
  </Record>
  <Record>
    <Row
      A="19"
      AW="A"
      BZ="2012-11-02 00:32:58.541265"
      CA="2012-11-02 00:32:58.541265"
      CB="1"
      CC="Friday"
    />
  </Record>
  <Record>
    <Row
      A="20"
      AW="A"
      BZ="2012-11-02 00:32:59.017964"
      CA="2012-11-02 00:32:59.017964"
      CB="2"
    />
  </Record>
  <Record>
    <Row
      A="21"
      AU="3"
      AW="A"
      BZ="2012-11-02 02:29:04.275486"
      CA="2012-11-02 02:29:04.275486"
      CB="3"
    />
  </Record>
  <Record>
    <Row
      A="22"
      B="education"
      AB="3"
      AU="2"
      AW="A"
      BZ="2012-11-02 03:12:08.048487"
      CA="2012-11-02 03:12:27.71298"
      CB="4"
    />
  </Record>
  <Record>
    <Row
      A="23"
      AU="4"
      AW="B"
      BZ="2012-11-02 03:36:37.166514"
      CA="2012-11-02 03:36:37.166514"
      CB="5"
    />
  </Record>
  <Record>
    <Row
      A="24"
      B="federal"
      AB="9"
      AU="2"
      AW="D"
      BQ="f"
      BR="f"
      BZ="2012-11-02 04:05:13.542617"
      CA="2012-11-02 04:05:55.361447"
      CB="6"
    />
  </Record>
  <Record>
    <Row
      A="25"
      B="study"
      AB="9"
      AT="01months"
      AU="IT"
      AW="D"
      BF="BSIT_ATT_NMM"
      BQ="t"
      BR="t"
      BS="Veteran"
      BZ="2012-11-02 04:06:50.953127"
      CA="2012-11-02 04:08:54.954222"
      CB="7"
    />
  </Record>
  <Record>
    <Row
      A="26"
      B="education"
      AB="2"
      AU="8"
      AW="A"
      BZ="2012-11-02 04:37:46.943814"
      CA="2012-11-02 04:38:02.363169"
      CB="8"
    />
  </Record>
  <Record>
    <Row
      A="27"
      B="education"
      AB="2"
      AU="8"
      AW="B"
      BZ="2012-11-02 04:38:53.139761"
      CA="2012-11-02 04:39:14.69773"
      CB="9"
    />
  </Record>
  <Record>
    <Row
      A="28"
      B="active"
      J="Adair"
      K="Wallace"
      O="adawa1@bellsouth.net"
      P="9194629030"
      T="2:00 PM"
      U="t"
      V="101 Huger Lane"
      W="cary"
      X="North Carolina"
      Y="United States"
      Z="27513"
      AB="7"
      AT="01months"
      AU="FSEM"
      AW="A"
      AY="BSFEM"
      BD="BSFEM"
      BQ="t"
      BR="t"
      BS="Veteran"
      BX="279"
      BY="2133"
      BZ="2012-11-02 05:21:00.337155"
      CA="2012-11-02 05:24:14.626338"
      CB="10"
    />
  </Record>
  <Record>
    <Row
      A="29"
      B="study"
      AB="6"
      AT="01months"
      AU="HS"
      AW="M"
      BE="MPH"
      BQ="t"
      BR="f"
      BZ="2012-11-02 05:21:09.974643"
      CA="2012-11-02 05:22:14.928446"
      CB="11"
    />
  </Record>
  <Record>
    <Row
      A="30"
      B="education"
      AB="2"
      AU="7"
      AW="M"
      BZ="2012-11-02 05:44:33.812572"
      CA="2012-11-02 05:44:40.072637"
      CB="12"
    />
  </Record>
  <Record>
    <Row
      A="31"
      B="active"
      J="Jim"
      K="Sumser"
      O="jim@apress.com"
      P="6502127030"
      T="afternoon"
      U="t"
      V="161 Laurie Meadows Dr."
      W="San mateo"
      X="CA"
      Y="USA"
      Z="94403"
      AB="3"
      AT="1"
      AU="4"
      AW="4"
      AY="METDBA"
      BB="METDBA"
      BC="AAPHDB"
      BZ="2012-11-02 05:53:59.289683"
      CA="2012-11-02 06:02:06.413549"
      CB="13"
    />
  </Record>
  <Record>
    <Row
      A="32"
      AU="8"
      AW="B"
      BZ="2012-11-02 07:23:45.517481"
      CA="2012-11-02 07:23:45.517481"
      CB="14"
    />
  </Record>
  <Record>
    <Row
      A="33"
      B="education"
      AB="1"
      AU="8"
      AW="B"
      BZ="2012-11-02 07:23:46.654543"
      CA="2012-11-02 07:24:06.15971"
      CB="15"
    />
  </Record>
  <Record>
    <Row
      A="34"
      B="federal"
      AB="6"
      AU="3"
      AW="A"
      BQ="t"
      BR="f"
      BZ="2012-11-02 10:32:17.964742"
      CA="2012-11-02 10:32:43.170973"
      CB="16"
    />
  </Record>
  <Record>
    <Row
      A="35"
      B="federal"
      AB="6"
      AU="2"
      AW="B"
      BQ="f"
      BR="f"
      BZ="2012-11-02 11:41:09.927716"
      CA="2012-11-02 11:44:52.029522"
      CB="17"
    />
  </Record>
  <Record>
    <Row
      A="36"
      B="active"
      J="krispies"
      K="zuniga"
      O="krispivallero88@yahoo.com"
      P="9565258874"
      T="9:00 AM"
      V="5001 Tierra Del Sol"
      W="Donna,TX"
      X="Texas"
      Y="United States"
      Z="78537"
      AB="5"
      AT="01months"
      AU="BIZ"
      AW="A"
      BQ="t"
      BR="f"
      BZ="2012-11-02 12:18:38.135165"
      CA="2012-11-02 12:21:51.048528"
      CB="18"
    />
  </Record>
  <Record>
    <Row
      A="37"
      B="federal"
      AB="6"
      AU="6"
      AW="M"
      BQ="t"
      BR="t"
      BS="Active"
      BZ="2012-11-02 12:19:35.035185"
      CA="2012-11-02 12:19:51.394948"
      CB="19"
    />
  </Record>
  <Record>
    <Row
      A="38"
      B="federal"
      AB="8"
      AU="2"
      AW="M"
      BQ="f"
      BR="f"
      BZ="2012-11-02 13:07:39.473984"
      CA="2012-11-02 13:08:08.216913"
      CB="20"
    />
  </Record>
  <Record>
    <Row
      A="39"
      B="study"
      AB="4"
      AT="3plusmonths"
      AW="B"
      BQ="t"
      BR="t"
      BS="Veteran"
      BZ="2012-11-02 14:05:47.548134"
      CA="2012-11-02 14:06:50.721924"
      CB="21"
    />
  </Record>
  <Record>
    <Row
      A="40"
      B="federal"
      AB="4"
      AU="1"
      AW="B"
      BQ="t"
      BR="f"
      BZ="2012-11-02 15:43:39.024307"
      CA="2012-11-02 15:44:33.19707"
      CB="22"
    />
  </Record>
  <Record>
    <Row
      A="41"
      B="study"
      AB="5"
      AT="23months"
      AU="PEP"
      AW="A"
      BI="MSEP"
      BQ="t"
      BR="f"
      BZ="2012-11-02 18:03:09.954894"
      CA="2012-11-02 18:04:28.005171"
      CB="23"
    />
  </Record>
  <Record>
    <Row
      A="42"
      B="federal"
      AB="4"
      AW="A"
      BQ="t"
      BR="f"
      BZ="2012-11-02 19:06:43.16363"
      CA="2012-11-02 19:07:37.638091"
      CB="24"
    />
  </Record>
  <Record>
    <Row
      A="43"
      B="education"
      AB="1"
      AU="2"
      AW="M"
      BZ="2012-11-02 19:49:26.164293"
      CA="2012-11-02 19:49:34.848874"
      CB="25"
    />
  </Record>
  <Record>
    <Row
      A="44"
      B="study"
      AB="1"
      AC="f"
      AD="English"
      AF="1985"
      AT="2"
      AU="5"
      AW="B"
      AZ="CJAOL"
      BQ="t"
      BR="f"
      BZ="2012-11-02 20:32:44.33249"
      CA="2012-11-02 20:33:59.771649"
      CB="26"
    />
  </Record>
  <Record>
    <Row
      A="45"
      AU="5"
      AW="A"
      BZ="2012-11-02 20:48:35.238512"
      CA="2012-11-02 20:48:35.238512"
      CB="27"
    />
  </Record>
  <Record>
    <Row
      A="46"
      B="federal"
      AB="4"
      AU="7"
      AW="A"
      BQ="t"
      BR="f"
      BZ="2012-11-02 21:00:25.253692"
      CA="2012-11-02 21:02:04.379162"
      CB="28"
    />
  </Record>
  <Record>
    <Row
      A="47"
      B="federal"
      AB="4"
      AU="7"
      AW="A"
      BQ="t"
      BR="f"
      BZ="2012-11-02 21:03:57.329153"
      CA="2012-11-02 21:04:15.726917"
      CB="29"
    />
  </Record>
  <Record>
    <Row
      A="48"
      B="federal"
      AB="4"
      AU="7"
      AW="A"
      BQ="t"
      BR="f"
      BZ="2012-11-02 21:04:01.287669"
      CA="2012-11-02 21:04:14.884185"
      CB="30"
    />
  </Record>
  <Record>
    <Row
      A="49"
      B="federal"
      AB="5"
      AU="7"
      AW="B"
      BQ="t"
      BR="f"
      BZ="2012-11-02 21:07:33.504769"
      CA="2012-11-02 21:07:44.852455"
      CB="31"
    />
  </Record>
  <Record>
    <Row
      A="50"
      B="study"
      AB="4"
      AT="12months"
      AU="PEP"
      AW="B"
      BI="MSEP"
      BQ="t"
      BR="f"
      BZ="2012-11-02 21:08:43.692534"
      CA="2012-11-02 21:10:08.524517"
      CB="32"
    />
  </Record>
  <Record>
    <Row
      A="51"
      B="federal"
      AB="6"
      AU="2"
      AW="M"
      BQ="t"
      BR="f"
      BZ="2012-11-02 21:10:53.79757"
      CA="2012-11-02 21:11:08.161678"
      CB="33"
    />
  </Record>
  <Record>
    <Row
      A="52"
      B="federal"
      AB="6"
      AU="7"
      AW="M"
      BQ="t"
      BR="f"
      BZ="2012-11-02 21:16:03.010602"
      CA="2012-11-02 21:16:11.925594"
      CB="34"
    />
  </Record>
  <Record>
    <Row
      A="53"
      AU="1"
      AW="M"
      BZ="2012-11-02 21:16:05.975336"
      CA="2012-11-02 21:16:05.975336"
      CB="35"
    />
  </Record>
  <Record>
    <Row
      A="54"
      B="federal"
      AB="6"
      AU="7"
      AW="B"
      BQ="t"
      BR="f"
      BS="Veteran"
      BZ="2012-11-02 21:18:38.681047"
      CA="2012-11-02 21:19:08.453527"
      CB="36"
    />
  </Record>
  <Record>
    <Row
      A="55"
      B="federal"
      AB="5"
      AU="7"
      AW="B"
      BQ="t"
      BR="f"
      BZ="2012-11-02 21:18:40.866705"
      CA="2012-11-02 21:19:00.456617"
      CB="37"
    />
  </Record>
  <Record>
    <Row
      A="56"
      AW="B"
      BZ="2012-11-02 21:26:54.681004"
      CA="2012-11-02 21:26:54.681004"
      CB="38"
    />
  </Record>
  <Record>
    <Row
      A="57"
      AU="4"
      AW="M"
      BZ="2012-11-02 21:30:30.185262"
      CA="2012-11-02 21:30:30.185262"
      CB="39"
    />
  </Record>
  <Record>
    <Row
      A="58"
      B="federal"
      AB="5"
      AU="3"
      AW="M"
      BQ="t"
      BR="f"
      BZ="2012-11-02 21:31:12.237051"
      CA="2012-11-02 21:31:30.68178"
      CB="40"
    />
  </Record>
  <Record>
    <Row
      A="59"
      B="study"
      AB="3"
      AC="f"
      AD="English"
      AF="1991"
      AT="2"
      AU="5"
      AW="B"
      AZ="CJBOL"
      BQ="t"
      BR="f"
      BZ="2012-11-02 21:33:38.756755"
      CA="2012-11-02 21:34:23.59723"
      CB="41"
    />
  </Record>
  <Record>
    <Row
      A="60"
      B="federal"
      AB="5"
      AU="2"
      AW="B"
      BQ="t"
      BR="t"
      BS="Veteran"
      BZ="2012-11-02 22:13:41.789822"
      CA="2012-11-02 22:14:14.592253"
      CB="42"
    />
  </Record>
  <Record>
    <Row
      A="61"
      B="education"
      BZ="2012-11-02 22:29:34.117802"
      CA="2012-11-02 22:30:47.264753"
      CB="43"
    />
  </Record>
  <Record>
    <Row
      A="62"
      AU="8"
      AW="M"
      BZ="2012-11-02 22:56:50.960361"
      CA="2012-11-02 22:56:50.960361"
      CB="44"
    />
  </Record>
  <Record>
    <Row
      A="63"
      AU="5"
      AW="B"
      BZ="2012-11-02 22:57:22.630043"
      CA="2012-11-02 22:57:22.630043"
      CB="45"
    />
  </Record>
  <Record>
    <Row
      A="64"
      B="federal"
      AB="4"
      AU="7"
      AW="M"
      BQ="t"
      BR="f"
      BZ="2012-11-02 23:47:48.228353"
      CA="2012-11-02 23:47:54.647814"
      CB="46"
    />
  </Record>
  <Record>
    <Row
      A="65"
      AU="4"
      AW="M"
      BZ="2012-11-02 23:48:07.474785"
      CA="2012-11-02 23:48:07.474785"
      CB="47"
    />
  </Record>
  <Record>
    <Row
      A="66"
      AU="5"
      AW="M"
      BZ="2012-11-02 23:48:12.295913"
      CA="2012-11-02 23:48:12.295913"
      CB="48"
    />
  </Record>
  <Record>
    <Row
      A="67"
      B="study"
      AT="1"
      AU="4"
      AW="4"
      BB="GBDBA"
      BC="AAPHDB"
      BZ="2012-11-02 23:48:24.120174"
      CA="2012-11-02 23:48:33.557489"
      CB="49"
    />
  </Record>
  <Record>
    <Row
      A="68"
      B="education"
      AB="4"
      AC="f"
      AD="English"
      AF="1983"
      AU="5"
      AW="B"
      BZ="2012-11-02 23:49:59.650787"
      CA="2012-11-02 23:50:13.202126"
      CB="50"
    />
  </Record>
  <Record>
    <Row
      A="69"
      B="education"
      AB="3"
      AU="8"
      AW="B"
      BZ="2012-11-02 23:56:29.934855"
      CA="2012-11-02 23:56:39.147155"
      CB="51"
    />
  </Record>
  <Record>
    <Row
      A="70"
      B="education"
      AB="5"
      AU="2"
      AW="B"
      BZ="2012-11-03 02:18:22.521473"
      CA="2012-11-03 02:18:27.587449"
      CB="1"
      CC="Saturday"
    />
  </Record>
  <Record>
    <Row
      A="71"
      B="education"
      AB="2"
      AU="1"
      AW="A"
      BZ="2012-11-03 02:32:16.45255"
      CA="2012-11-03 02:32:31.717039"
      CB="2"
    />
  </Record>
  <Record>
    <Row
      A="72"
      AU="3"
      AW="D"
      BZ="2012-11-03 04:34:23.126373"
      CA="2012-11-03 04:34:23.126373"
      CB="3"
    />
  </Record>
  <Record>
    <Row
      A="73"
      AU="4"
      AW="B"
      BZ="2012-11-03 04:48:55.835277"
      CA="2012-11-03 04:48:55.835277"
      CB="4"
    />
  </Record>
  <Record>
    <Row
      A="74"
      B="education"
      AB="7"
      AU="1"
      AW="B"
      BZ="2012-11-03 08:35:29.651857"
      CA="2012-11-03 08:36:56.124817"
      CB="5"
    />
  </Record>
  <Record>
    <Row
      A="75"
      B="study"
      AB="9"
      AT="3plusmonths"
      AU="NUR"
      AW="A"
      BH="MSN"
      BQ="t"
      BR="f"
      BZ="2012-11-03 09:08:39.666945"
      CA="2012-11-03 09:17:11.862786"
      CB="6"
    />
  </Record>
  <Record>
    <Row
      A="76"
      B="education"
      AB="2"
      AU="2"
      AW="A"
      BZ="2012-11-03 14:17:16.475296"
      CA="2012-11-03 14:17:25.366373"
      CB="7"
    />
  </Record>
  <Record>
    <Row
      A="77"
      B="education"
      AB="3"
      AU="2"
      AW="A"
      BZ="2012-11-03 14:17:58.175187"
      CA="2012-11-03 14:18:11.369188"
      CB="8"
    />
  </Record>
  <Record>
    <Row
      A="78"
      AU="1"
      AW="A"
      BZ="2012-11-03 14:22:26.227842"
      CA="2012-11-03 14:22:26.227842"
      CB="9"
    />
  </Record>
  <Record>
    <Row
      A="79"
      B="federal"
      AB="7"
      AU="3"
      AW="B"
      BQ="t"
      BR="f"
      BZ="2012-11-03 14:43:12.605112"
      CA="2012-11-03 14:43:37.932649"
      CB="10"
    />
  </Record>
  <Record>
    <Row
      A="80"
      B="education"
      AB="1"
      AU="6"
      AW="A"
      BZ="2012-11-03 15:11:13.7287"
      CA="2012-11-03 15:11:56.637798"
      CB="11"
    />
  </Record>
  <Record>
    <Row
      A="81"
      B="education"
      AB="2"
      AU="1"
      AW="A"
      BZ="2012-11-03 17:15:56.640082"
      CA="2012-11-03 17:16:08.822589"
      CB="12"
    />
  </Record>
  <Record>
    <Row
      A="82"
      AU="1"
      AW="B"
      BZ="2012-11-03 18:18:19.276839"
      CA="2012-11-03 18:18:19.276839"
      CB="13"
    />
  </Record>
  <Record>
    <Row
      A="83"
      AU="3"
      AW="M"
      BZ="2012-11-03 18:21:02.190637"
      CA="2012-11-03 18:21:02.190637"
      CB="14"
    />
  </Record>
  <Record>
    <Row
      A="84"
      AU="5"
      AW="M"
      BZ="2012-11-03 18:55:15.777993"
      CA="2012-11-03 18:55:15.777993"
      CB="15"
    />
  </Record>
  <Record>
    <Row
      A="85"
      B="federal"
      AB="6"
      AT="01months"
      AU="CJ"
      AW="A"
      BB="MSCJ"
      BQ="f"
      BR="f"
      BZ="2012-11-03 19:25:51.242123"
      CA="2012-11-03 19:29:57.916187"
      CB="16"
    />
  </Record>
  <Record>
    <Row
      A="86"
      B="education"
      AB="3"
      AU="1"
      AW="A"
      BZ="2012-11-03 20:02:31.598264"
      CA="2012-11-03 20:02:48.23003"
      CB="17"
    />
  </Record>
  <Record>
    <Row
      A="87"
      B="education"
      AB="3"
      AW="A"
      BZ="2012-11-03 20:57:24.588967"
      CA="2012-11-03 20:57:43.989145"
      CB="18"
    />
  </Record>
  <Record>
    <Row
      A="88"
      B="education"
      AB="3"
      AU="6"
      AW="A"
      BZ="2012-11-03 20:59:13.68868"
      CA="2012-11-03 20:59:22.788865"
      CB="19"
    />
  </Record>
  <Record>
    <Row
      A="89"
      B="education"
      AB="3"
      AU="1"
      AW="B"
      BZ="2012-11-03 21:05:44.486159"
      CA="2012-11-03 21:05:50.325179"
      CB="20"
    />
  </Record>
  <Record>
    <Row
      A="90"
      AU="4"
      AW="B"
      BZ="2012-11-03 21:45:34.413052"
      CA="2012-11-03 21:45:34.413052"
      CB="21"
    />
  </Record>
  <Record>
    <Row
      A="91"
      AU="1"
      AW="B"
      BZ="2012-11-03 21:45:42.28788"
      CA="2012-11-03 21:45:42.28788"
      CB="22"
    />
  </Record>
  <Record>
    <Row
      A="92"
      AU="6"
      AW="B"
      BZ="2012-11-03 21:45:47.419108"
      CA="2012-11-03 21:45:47.419108"
      CB="23"
    />
  </Record>
  <Record>
    <Row
      A="94"
      B="education"
      AB="8"
      AU="1"
      AW="A"
      BZ="2012-11-03 21:52:10.283619"
      CA="2012-11-03 21:52:18.04096"
      CB="24"
    />
  </Record>
  <Record>
    <Row
      A="95"
      B="education"
      AB="5"
      AU="3"
      AW="A"
      BZ="2012-11-03 22:10:01.710309"
      CA="2012-11-03 22:10:11.006461"
      CB="25"
    />
  </Record>
  <Record>
    <Row
      A="96"
      B="education"
      AB="5"
      AU="3"
      AW="B"
      BZ="2012-11-03 22:40:22.890943"
      CA="2012-11-03 22:42:59.792888"
      CB="26"
    />
  </Record>
  <Record>
    <Row
      A="97"
      B="education"
      AB="3"
      AU="2"
      AW="M"
      BZ="2012-11-03 22:50:36.823953"
      CA="2012-11-03 22:50:41.411025"
      CB="27"
    />
  </Record>
  <Record>
    <Row
      A="98"
      B="education"
      AB="2"
      AU="2"
      AW="M"
      BZ="2012-11-03 22:53:25.669521"
      CA="2012-11-03 22:53:30.984116"
      CB="28"
    />
  </Record>
  <Record>
    <Row
      A="99"
      B="education"
      AB="0"
      AT="01months"
      AU="FSEM"
      AW="B"
      BB="MSCJ_CORR"
      BD="BSFS"
      BQ="t"
      BR="f"
      BZ="2012-11-03 22:58:05.651437"
      CA="2012-11-03 23:01:01.293318"
      CB="29"
    />
  </Record>
  <Record>
    <Row
      A="103"
      AU="2"
      AW="M"
      BZ="2012-11-03 23:13:34.1209"
      CA="2012-11-03 23:13:34.1209"
      CB="30"
    />
  </Record>
  <Record>
    <Row
      A="104"
      B="federal"
      AB="6"
      AU="2"
      AW="M"
      BQ="t"
      BR="f"
      BZ="2012-11-03 23:29:47.313876"
      CA="2012-11-03 23:29:55.422149"
      CB="31"
    />
  </Record>
  <Record>
    <Row
      A="105"
      AU="4"
      AW="M"
      BZ="2012-11-03 23:34:17.674584"
      CA="2012-11-03 23:34:17.674584"
      CB="32"
    />
  </Record>
  <Record>
    <Row
      A="106"
      AU="3"
      AW="B"
      BZ="2012-11-03 23:34:23.55122"
      CA="2012-11-03 23:34:23.55122"
      CB="33"
    />
  </Record>
  <Record>
    <Row
      A="107"
      AU="2"
      AW="M"
      BZ="2012-11-03 23:36:22.505307"
      CA="2012-11-03 23:36:22.505307"
      CB="34"
    />
  </Record>
  <Record>
    <Row
      A="108"
      AU="2"
      AW="M"
      BZ="2012-11-03 23:45:52.051016"
      CA="2012-11-03 23:45:52.051016"
      CB="35"
    />
  </Record>
  <Record>
    <Row
      A="109"
      AU="2"
      AW="B"
      BZ="2012-11-04 00:07:30.283334"
      CA="2012-11-04 00:07:30.283334"
      CB="1"
      CC="Sunday"
    />
  </Record>
  <Record>
    <Row
      A="111"
      AU="1"
      AW="B"
      BZ="2012-11-04 00:14:12.65809"
      CA="2012-11-04 00:14:12.65809"
      CB="2"
    />
  </Record>
  <Record>
    <Row
      A="112"
      B="education"
      AB="5"
      AU="1"
      AW="A"
      BZ="2012-11-04 00:21:27.769213"
      CA="2012-11-04 00:21:44.77391"
      CB="3"
    />
  </Record>
  <Record>
    <Row
      A="113"
      B="study"
      AB="1"
      AC="f"
      AD="English"
      AF="1984"
      AT="1"
      AU="CJ"
      AW="B"
      AZ="ACAOL"
      BB="MSCJ_GICJ"
      BQ="t"
      BR="f"
      BS="Active"
      BZ="2012-11-04 00:25:30.80457"
      CA="2012-11-04 00:26:03.44447"
      CB="4"
    />
  </Record>
  <Record>
    <Row
      A="114"
      B="study"
      AB="3"
      AT="2"
      AU="PEP"
      AW="4"
      BB="ACSDBA"
      BC="AAPHDB"
      BI="MSEP"
      BQ="t"
      BR="f"
      BZ="2012-11-04 00:40:54.299869"
      CA="2012-11-04 00:44:14.685087"
      CB="5"
    />
  </Record>
  <Record>
    <Row
      A="115"
      B="education"
      AB="1"
      AU="3"
      AW="A"
      BZ="2012-11-04 01:03:54.062298"
      CA="2012-11-04 01:04:00.3392"
      CB="6"
    />
  </Record>
  <Record>
    <Row
      A="116"
      B="education"
      AB="2"
      AU="3"
      AW="B"
      BZ="2012-11-04 02:41:35.715433"
      CA="2012-11-04 02:41:40.609776"
      CB="7"
    />
  </Record>
  <Record>
    <Row
      A="117"
      AU="6"
      AW="A"
      BZ="2012-11-04 04:10:00.692049"
      CA="2012-11-04 04:10:00.692049"
      CB="8"
    />
  </Record>
  <Record>
    <Row
      A="118"
      B="study"
      AB="2"
      AC="f"
      AD="English"
      AF="2010"
      AT="2"
      AU="5"
      AW="A"
      AZ="CJAOL"
      BQ="t"
      BR="f"
      BZ="2012-11-04 04:39:57.209332"
      CA="2012-11-04 04:40:49.292657"
      CB="9"
    />
  </Record>
  <Record>
    <Row
      A="119"
      B="study"
      AB="2"
      AC="f"
      AD="English"
      AF="1980"
      AT="2"
      AU="1"
      AW="A"
      AZ="ACAOL"
      BQ="f"
      BR="f"
      BZ="2012-11-04 04:57:37.905657"
      CA="2012-11-04 04:59:40.911648"
      CB="10"
    />
  </Record>
  <Record>
    <Row
      A="120"
      AU="2"
      AW="B"
      BZ="2012-11-04 05:05:32.647833"
      CA="2012-11-04 05:05:32.647833"
      CB="11"
    />
  </Record>
  <Record>
    <Row
      A="121"
      AU="2"
      AW="B"
      BZ="2012-11-04 05:05:41.681763"
      CA="2012-11-04 05:05:41.681763"
      CB="12"
    />
  </Record>
  <Record>
    <Row
      A="122"
      B="study"
      AB="3"
      AT="01months"
      AU="HS"
      AW="B"
      BE="MSHE"
      BQ="t"
      BR="f"
      BZ="2012-11-04 05:53:58.512044"
      CA="2012-11-04 05:54:27.876289"
      CB="13"
    />
  </Record>
  <Record>
    <Row
      A="123"
      AU="4"
      AW="B"
      BZ="2012-11-04 05:54:45.697973"
      CA="2012-11-04 05:54:45.697973"
      CB="14"
    />
  </Record>
  <Record>
    <Row
      A="124"
      B="study"
      AB="1"
      AC="f"
      AD="English"
      AF="2003"
      AT="4"
      AU="5"
      AW="A"
      AZ="CINOL"
      BQ="t"
      BR="f"
      BZ="2012-11-04 06:02:13.786626"
      CA="2012-11-04 06:02:56.85085"
      CB="15"
    />
  </Record>
  <Record>
    <Row
      A="125"
      B="active"
      J="Laura"
      K="Spoerl"
      O="lauraspoerl@yahoo.com"
      P="5635649901"
      T="7:00 PM"
      U="t"
      V="1603 Central avenue #6"
      W="Dubuque"
      X="Iowa"
      Y="United States"
      Z="52001"
      AB="5"
      AT="23months"
      AU="HS"
      AW="A"
      AY="AASMOM"
      BE="AASMOM"
      BQ="t"
      BR="f"
      BS="No"
      BX="279"
      BY="2133"
      BZ="2012-11-04 06:18:57.270103"
      CA="2012-11-04 06:20:54.737393"
      CB="16"
    />
  </Record>
  <Record>
    <Row
      A="126"
      B="study"
      AB="3"
      AT="3plusmonths"
      AU="HS"
      AW="B"
      BE="BSHS"
      BQ="t"
      BR="f"
      BZ="2012-11-04 11:35:01.311901"
      CA="2012-11-04 11:35:50.260108"
      CB="17"
    />
  </Record>
  <Record>
    <Row
      A="127"
      B="federal"
      AB="4"
      AU="2"
      AW="M"
      BQ="f"
      BR="f"
      BZ="2012-11-04 17:05:15.508997"
      CA="2012-11-04 17:07:59.584045"
      CB="18"
    />
  </Record>
  <Record>
    <Row
      A="128"
      B="federal"
      AB="4"
      AU="3"
      AW="D"
      BQ="t"
      BR="f"
      BZ="2012-11-04 19:01:55.370168"
      CA="2012-11-04 19:02:28.02341"
      CB="19"
    />
  </Record>
  <Record>
    <Row
      A="129"
      B="study"
      AB="4"
      AT="23months"
      AU="HS"
      AW="A"
      BQ="t"
      BR="f"
      BZ="2012-11-04 19:11:52.720784"
      CA="2012-11-04 19:12:30.782313"
      CB="20"
    />
  </Record>
  <Record>
    <Row
      A="130"
      B="federal"
      AB="2"
      AU="1"
      AW="B"
      BQ="t"
      BR="f"
      BZ="2012-11-04 20:09:50.195971"
      CA="2012-11-04 20:10:06.161434"
      CB="21"
    />
  </Record>
  <Record>
    <Row
      A="131"
      B="study"
      AB="5"
      AT="01months"
      AU="CJ"
      AW="M"
      BB="MSCJ_CORR"
      BQ="t"
      BR="f"
      BZ="2012-11-04 20:13:22.485013"
      CA="2012-11-04 20:13:57.779971"
      CB="22"
    />
  </Record>
  <Record>
    <Row
      A="132"
      B="education"
      AB="3"
      AU="2"
      AW="B"
      BZ="2012-11-04 20:32:01.355095"
      CA="2012-11-04 20:32:04.348278"
      CB="23"
    />
  </Record>
  <Record>
    <Row
      A="133"
      B="federal"
      AB="2"
      AU="3"
      AW="B"
      BQ="t"
      BR="f"
      BZ="2012-11-04 20:41:31.706566"
      CA="2012-11-04 20:41:38.935786"
      CB="24"
    />
  </Record>
  <Record>
    <Row
      A="134"
      AU="1"
      AW="D"
      BZ="2012-11-04 21:02:01.741638"
      CA="2012-11-04 21:02:01.741638"
      CB="25"
    />
  </Record>
  <Record>
    <Row
      A="135"
      AU="2"
      AW="M"
      BZ="2012-11-04 21:08:16.838249"
      CA="2012-11-04 21:08:16.838249"
      CB="26"
    />
  </Record>
  <Record>
    <Row
      A="136"
      AU="4"
      AW="M"
      BZ="2012-11-04 21:10:43.052356"
      CA="2012-11-04 21:10:43.052356"
      CB="27"
    />
  </Record>
  <Record>
    <Row
      A="137"
      AU="5"
      AW="M"
      BZ="2012-11-04 21:10:48.993576"
      CA="2012-11-04 21:10:48.993576"
      CB="28"
    />
  </Record>
  <Record>
    <Row
      A="138"
      AU="1"
      AW="M"
      BZ="2012-11-04 21:10:55.347055"
      CA="2012-11-04 21:10:55.347055"
      CB="29"
    />
  </Record>
  <Record>
    <Row
      A="139"
      AU="3"
      AW="M"
      BZ="2012-11-04 21:11:02.149484"
      CA="2012-11-04 21:11:02.149484"
      CB="30"
    />
  </Record>
  <Record>
    <Row
      A="140"
      AU="3"
      AW="M"
      BZ="2012-11-04 21:11:06.12622"
      CA="2012-11-04 21:11:06.12622"
      CB="31"
    />
  </Record>
  <Record>
    <Row
      A="141"
      AU="4"
      AW="M"
      BZ="2012-11-04 21:11:12.354825"
      CA="2012-11-04 21:11:12.354825"
      CB="32"
    />
  </Record>
  <Record>
    <Row
      A="142"
      AU="1"
      AW="A"
      BZ="2012-11-04 21:32:28.305358"
      CA="2012-11-04 21:32:28.305358"
      CB="33"
    />
  </Record>
  <Record>
    <Row
      A="143"
      B="active"
      J="cynthia"
      K="crawford"
      O="crwfrdcynthj@yahoo.com"
      P="9548547807"
      T="7:00 PM"
      U="t"
      V="12806 sw 52 st miramar"
      W="miramar"
      X="Florida"
      Y="United States"
      Z="33027"
      AB="2"
      AT="01months"
      AU="BIZ"
      AW="A"
      AY="MSM_LSM"
      BA="MSM_LSM"
      BQ="t"
      BR="f"
      BS="No"
      BX="279"
      BY="2135"
      BZ="2012-11-04 21:37:20.765106"
      CA="2012-11-04 21:39:51.715835"
      CB="34"
    />
  </Record>
  <Record>
    <Row
      A="144"
      AU="1"
      AW="M"
      BZ="2012-11-04 22:07:28.692787"
      CA="2012-11-04 22:07:28.692787"
      CB="35"
    />
  </Record>
  <Record>
    <Row
      A="145"
      AU="3"
      AW="M"
      BZ="2012-11-04 22:19:12.570489"
      CA="2012-11-04 22:19:12.570489"
      CB="36"
    />
  </Record>
  <Record>
    <Row
      A="146"
      AW="A"
      BZ="2012-11-04 22:33:02.882692"
      CA="2012-11-04 22:33:02.882692"
      CB="37"
    />
  </Record>
  <Record>
    <Row
      A="147"
      AU="1"
      AW="A"
      BZ="2012-11-04 22:38:23.122064"
      CA="2012-11-04 22:38:23.122064"
      CB="38"
    />
  </Record>
  <Record>
    <Row
      A="148"
      B="federal"
      AB="3"
      AU="3"
      AW="A"
      BQ="t"
      BR="f"
      BZ="2012-11-04 22:55:57.930636"
      CA="2012-11-04 22:57:37.872223"
      CB="39"
    />
  </Record>
  <Record>
    <Row
      A="149"
      B="study"
      AB="2"
      AT="01months"
      AU="HS"
      AW="M"
      BQ="t"
      BR="f"
      BZ="2012-11-04 23:44:45.345675"
      CA="2012-11-04 23:45:47.171649"
      CB="40"
    />
  </Record>
  <Record>
    <Row
      A="150"
      B="education"
      AB="1"
      AT="2"
      AU="4"
      AW="5"
      BC="XX"
      BZ="2012-11-04 23:58:54.867775"
      CA="2012-11-05 00:01:28.281968"
      CB="41"
    />
  </Record>
  <Record>
    <Row
      A="151"
      B="education"
      AU="3"
      AW="M"
      BZ="2012-11-05 01:42:32.53164"
      CA="2012-11-05 01:43:03.73723"
      CB="1"
      CC="Monday"
    />
  </Record>
  <Record>
    <Row
      A="152"
      B="study"
      AB="2"
      AC="f"
      AD="English"
      AF="1989"
      AT="2"
      AU="5"
      AW="B"
      AZ="AMAOL"
      BQ="t"
      BR="f"
      BZ="2012-11-05 01:47:12.421879"
      CA="2012-11-05 01:47:51.232597"
      CB="2"
    />
  </Record>
  <Record>
    <Row
      A="153"
      B="active"
      J="John"
      K="Halpin"
      O="matthalpin@sbcglobal.net"
      P="2105235172"
      T="2:00 PM"
      U="t"
      V="8546 braun knoll"
      W="San Antonio"
      X="Texas"
      Y="United States"
      Z="78254"
      AB="5"
      AT="01months"
      AU="PEP"
      AW="A"
      AY="MSEP"
      BI="MSEP"
      BQ="t"
      BR="t"
      BS="Veteran"
      BX="279"
      BY="2135"
      BZ="2012-11-05 01:50:53.159187"
      CA="2012-11-05 01:55:49.550115"
      CB="3"
    />
  </Record>
  <Record>
    <Row
      A="154"
      B="federal"
      AB="5"
      AU="3"
      AW="A"
      BQ="t"
      BR="f"
      BZ="2012-11-05 03:26:38.379293"
      CA="2012-11-05 03:27:24.029951"
      CB="4"
    />
  </Record>
  <Record>
    <Row
      A="155"
      AU="6"
      AW="A"
      BZ="2012-11-05 03:37:24.840701"
      CA="2012-11-05 03:37:24.840701"
      CB="5"
    />
  </Record>
  <Record>
    <Row
      A="156"
      B="education"
      AB="4"
      AC="f"
      AD="English"
      AF="1980"
      AT="1"
      AU="5"
      BC="AAPHDB"
      BQ="t"
      BR="f"
      BZ="2012-11-05 04:28:29.548928"
      CA="2012-11-05 04:40:52.648207"
      CB="6"
    />
  </Record>
  <Record>
    <Row
      A="157"
      B="education"
      AB="8"
      AU="2"
      AW="D"
      BZ="2012-11-05 05:05:20.426527"
      CA="2012-11-05 05:05:34.389842"
      CB="7"
    />
  </Record>
  <Record>
    <Row
      A="158"
      B="federal"
      AB="4"
      AU="6"
      AW="A"
      BQ="t"
      BR="t"
      BZ="2012-11-05 06:02:47.826088"
      CA="2012-11-05 06:03:16.612713"
      CB="8"
    />
  </Record>
  <Record>
    <Row
      A="159"
      BZ="2012-11-05 06:23:14.078934"
      CA="2012-11-05 06:23:14.078934"
      CB="9"
    />
  </Record>
  <Record>
    <Row
      A="160"
      B="federal"
      AB="4"
      AU="6"
      AW="A"
      BQ="f"
      BR="f"
      BZ="2012-11-05 13:14:41.934435"
      CA="2012-11-05 13:17:40.288549"
      CB="10"
    />
  </Record>
  <Record>
    <Row
      A="161"
      B="active"
      J="juan"
      K="benjamin"
      O="juanbenjamin1@yahoo.com"
      P="3138286555"
      T="11:00 AM"
      U="t"
      V="18889 Dalby st"
      W="Redford"
      X="Michigan"
      Y="United States"
      Z="48240"
      AB="3"
      AT="12months"
      AU="HS"
      AW="A"
      AY="AASHI"
      BE="AASHI"
      BQ="t"
      BR="t"
      BS="Veteran"
      BX="279"
      BY="2133"
      BZ="2012-11-05 14:16:47.970487"
      CA="2012-11-05 14:18:33.957519"
      CB="11"
    />
  </Record>
  <Record>
    <Row
      A="162"
      AW="A"
      BZ="2012-11-05 14:20:47.43933"
      CA="2012-11-05 14:20:47.43933"
      CB="12"
    />
  </Record>
  <Record>
    <Row
      A="163"
      B="active"
      J="Irene"
      K="Nanao"
      O="imcu_nurz@yahoo.com"
      P="5865651811"
      T="10:00 AM"
      U="t"
      V="17283 suffield drive"
      W="clinton township"
      X="Michigan"
      Y="United States"
      Z="48038"
      AB="6"
      AL="t"
      AM="t"
      AT="01months"
      AU="NUR"
      AW="M"
      AY="MSN_FNP"
      BH="MSN_FNP"
      BQ="t"
      BR="f"
      BS="No"
      BX="222"
      BY="2139"
      BZ="2012-11-05 14:36:35.206249"
      CA="2012-11-05 14:38:36.427493"
      CB="13"
    />
  </Record>
  <Record>
    <Row
      A="164"
      B="active"
      J="Robert"
      K="Smyth"
      O="paul3419@gmail.com"
      P="6195047438"
      T="10:00 AM"
      U="t"
      V="10001 Dunbar la 2"
      W="El cajon"
      X="California"
      Y="United States"
      Z="92021"
      AB="5"
      AT="12months"
      AU="BIZ"
      AW="B"
      AY="MBA"
      BA="MBA"
      BQ="t"
      BR="f"
      BS="No"
      BX="279"
      BY="2135"
      BZ="2012-11-05 14:39:58.420491"
      CA="2012-11-05 14:43:38.374104"
      CB="14"
    />
  </Record>
  <Record>
    <Row
      A="165"
      AU="6"
      AW="A"
      BZ="2012-11-05 15:09:50.494364"
      CA="2012-11-05 15:09:50.494364"
      CB="15"
    />
  </Record>
  <Record>
    <Row
      A="166"
      G="153"
      BZ="2012-11-05 15:11:18.166923"
      CA="2012-11-05 15:11:18.166923"
      CB="16"
    />
  </Record>
  <Record>
    <Row
      A="167"
      B="federal"
      AB="6"
      AW="M"
      BQ="f"
      BR="f"
      BZ="2012-11-05 15:51:38.076317"
      CA="2012-11-05 15:53:01.431863"
      CB="17"
    />
  </Record>
  <Record>
    <Row
      A="168"
      AU="3"
      AW="A"
      BZ="2012-11-05 17:11:03.857046"
      CA="2012-11-05 17:11:03.857046"
      CB="18"
    />
  </Record>
  <Record>
    <Row
      A="169"
      AU="3"
      AW="A"
      BZ="2012-11-05 17:19:23.121973"
      CA="2012-11-05 17:19:23.121973"
      CB="19"
    />
  </Record>
  <Record>
    <Row
      A="170"
      AU="1"
      AW="A"
      BZ="2012-11-05 17:29:38.640531"
      CA="2012-11-05 17:29:38.640531"
      CB="20"
    />
  </Record>
  <Record>
    <Row
      A="171"
      B="education"
      AB="8"
      AU="1"
      AW="M"
      BZ="2012-11-05 18:24:59.510744"
      CA="2012-11-05 18:25:07.547726"
      CB="21"
    />
  </Record>
  <Record>
    <Row
      A="172"
      B="education"
      AB="1"
      AU="3"
      AW="D"
      BZ="2012-11-05 18:42:28.235966"
      CA="2012-11-05 18:42:58.907807"
      CB="22"
    />
  </Record>
  <Record>
    <Row
      A="173"
      AU="4"
      AW="B"
      BZ="2012-11-05 18:56:05.44769"
      CA="2012-11-05 18:56:05.44769"
      CB="23"
    />
  </Record>
  <Record>
    <Row
      A="174"
      B="education"
      AB="3"
      AU="2"
      AW="A"
      BZ="2012-11-05 19:05:08.849853"
      CA="2012-11-05 19:05:18.555429"
      CB="24"
    />
  </Record>
  <Record>
    <Row
      A="175"
      AU="2"
      AW="A"
      BZ="2012-11-05 19:08:06.122856"
      CA="2012-11-05 19:08:06.122856"
      CB="25"
    />
  </Record>
  <Record>
    <Row
      AB="7.43952533089913E-02"
    />
  </Record>
</Records>